BERTSimilarWords/BERTSimilarWords.py
BERTSimilarWords/__init__.py
BERTSimilarWords-0.0.13.dist-info/LICENSE.txt
BERTSimilarWords-0.0.13.dist-info/METADATA
BERTSimilarWords-0.0.13.dist-info/WHEEL
BERTSimilarWords-0.0.13.dist-info/top_level.txt
BERTSimilarWords-0.0.13.dist-info/RECORD
