Metadata-Version: 2.1
Name: BERTSimilarWords
Version: 0.0.13
Summary: Find Similar Words using BERT
Home-page: https://github.com/rdpahalavan/BERTSimilarWords
Author: Pahalavan R D
Author-email: rdpahalavan24@gmail.com
License: MIT
Keywords: BERT NLP
Platform: UNKNOWN
Classifier: Programming Language :: Python :: 3
Classifier: License :: OSI Approved :: MIT License
Classifier: Operating System :: OS Independent
Requires-Python: >=3.7.0
License-File: LICENSE.txt
Requires-Dist: torch (>=1.13.0)
Requires-Dist: numpy (>=1.21.0)
Requires-Dist: nltk (>=3.7)
Requires-Dist: wikipedia (>=1.4.0)
Requires-Dist: transformers (>=4.25.0)
Requires-Dist: scikit-learn (>=1.0.0)
Requires-Dist: tqdm (>=4.64.0)
Requires-Dist: setuptools (>=57.4.0)
Requires-Dist: python-docx (>=0.8.0)
